setup.cfg
setup.py
quiver/__init__.py
quiver/plotter.py
quiver.egg-info/PKG-INFO
quiver.egg-info/SOURCES.txt
quiver.egg-info/dependency_links.txt
quiver.egg-info/pbr.json
quiver.egg-info/requires.txt
quiver.egg-info/top_level.txt