Metadata-Version: 1.1
Name: quiver
Version: 0.1
Summary: A simple library to plot direction fields
Home-page: https://github.com/davidsoncasey/quiver
Author: Casey Davidson
Author-email: jdavids2@gmail.com
License: MIT
Download-URL: https://github.com/davidsoncasey/quiver/tarball/0.1
Keywords: plotting,direction field,differential equation
Platform: UNKNOWN
